{
    "data":[
        {
          "Nom": "Abélia Edouard Goucher",
          "N. scientifique ": "Abelia x 'Edouard Goucher'",
          "Famille ": "Caprifoliacées",
          "Origine ": "horticole",
          "Floraison": "fin de l'été",
          "Fleurs ": [
            "     ",
            "   blanc rosé "
          ],
          "Type": "arbuste ornemental",
          "Végétation": "arbustive",
          "Feuillage ": "persistant",
          "Hauteur": "1,80 m à 2,40 m",
          "Rusticité ": [
            "  ",
            " ",
            "  rustique jusqu'à -18°C "
          ],
          "Exposition ": [
            "  ",
            " ",
            "  ensoleillée à mi-ombre "
          ],
          "Sol": "tolérant",
          "Acidité ": "légèrement acide à légèrement alcalin",
          "Humidité ": "normal",
          "Utilisation": "isolé, fond de massif, haie",
          "Plantation": "automne, printemps",
          "Multiplication": "bouturage"
        },
        {
          "Nom": "Abélia de Chine",
          "N. scientifique ": "Abelia chinensis",
          "Synonymes ": "Abelia aschersoniana, A. cavaleriei,  A. chinensis var ionandra",
          "Famille ": "Caprifoliacées",
          "Origine ": "Chine",
          "Floraison": "août à septembre",
          "Fleurs ": [
            "     ",
            "   blanc, parfois rosé "
          ],
          "Type": "arbuste ornemental",
          "Végétation": "arbustive",
          "Feuillage ": "caduc à semi-persistant",
          "Hauteur": "1 m à 2 m",
          "Rusticité ": [
            "  ",
            " ",
            "  rustique jusqu'à -12°C "
          ],
          "Exposition ": [
            "  ",
            " ",
            "  ensoleillée à mi-ombre "
          ],
          "Sol": "tolérant",
          "Acidité ": "légèrement acide à légèrement alcalin",
          "Humidité ": "normal",
          "Utilisation": "isolé, fond de massif, haie",
          "Plantation": "automne, printemps",
          "Multiplication": "bouture, semis"
        },
        {
          "Nom": "Abélia",
          "N. scientifique ": "Abelia",
          "Famille ": "Caprifoliacées",
          "Origine ": "Asie",
          "Floraison": "de mai aux gelées",
          "Fleurs ": [
            "     ",
            "   rosée "
          ],
          "Type": "arbuste à fleurs",
          "Végétation": "vivace",
          "Feuillage ": "persistant",
          "Hauteur": "2 m",
          "Rusticité ": [
            "  ",
            " ",
            "  rustique "
          ],
          "Exposition ": [
            "  ",
            "  soleil "
          ],
          "Sol": "ordinaire, léger",
          "Acidité ": "neutre",
          "Humidité ": "normal",
          "Utilisation": "haie taillée, haie libre, isolé",
          "Plantation": "printemps, automne",
          "Multiplication": "bouturage en juillet",
          "Sensibilité ": "résistants aux ravageurs et aux maladies"
        },
        {
          "Nom": "Tulipier de Virginie, Arbre aux lis",
          "N. scientifique ": "Liriodendron tulipifera",
          "Famille ": "Magnoliacées",
          "Origine ": "sud et de est des États-Unis",
          "Floraison": "juillet à août",
          "Fleurs ": [
            "     ",
            "   jaune "
          ],
          "Type": "arbre à fleur",
          "Végétation": "vivace",
          "Feuillage ": "caduc",
          "Hauteur": "30 à 40 m",
          "Rusticité ": "   très rustique, -34°C ",
          "Exposition ": [
            "  ",
            " ",
            "  ensoleillée à mi-ombre "
          ],
          "Sol": "profond et fertile",
          "Acidité ": "légèrement acide à basique",
          "Humidité ": "sol normal à frais",
          "Utilisation": "arbre isolé",
          "Plantation": "automne",
          "Multiplication": "semis, marcottage"
        },
        {
          "Nom": "Robinier faux acacia, Carouge, Cassie",
          "N. scientifique ": "Robinia pseudoacacia",
          "Famille ": "Légumineuses, Fabacées, Papilionacées",
          "Origine ": "Amérique du nord",
          "Floraison": "mai à juillet",
          "Fleurs ": [
            "     ",
            "   blanche, rouge pour certaines variétés "
          ],
          "Type": "arbre",
          "Végétation": "vivace",
          "Feuillage ": "caduc",
          "Hauteur": "10 à 25 m",
          "Toxicité": "en dehors des fleurs, toutes les parties sont toxiques",
          "Rusticité ": [
            "  ",
            " ",
            " ",
            "  très rustique, -24°C "
          ],
          "Exposition ": [
            "  ",
            " ",
            "  ensoleillée à mi-ombre "
          ],
          "Sol": "tolérant",
          "Acidité ": "acide à basique",
          "Humidité ": "normal",
          "Utilisation": "ornementale, fleurs médicinales et comestibles, bois de qualité",
          "Plantation": "printemps",
          "Multiplication": "semis, rejets de souche, greffe"
        },
        {
          "Nom": "Rhododendron auriculé",
          "N. scientifique ": "Rhododendron auriculatum",
          "Famille ": "Ericacées",
          "Origine ": "Chine",
          "Floraison": "juillet",
          "Fleurs ": [
            "     ",
            "   blanche, parfois rosée "
          ],
          "Type": "petit arbre à fleurs",
          "Végétation": "vivace",
          "Feuillage ": "persistant",
          "Hauteur": "jusqu'à 10 m",
          "Rusticité ": [
            "  ",
            " ",
            " ",
            "  très rustique, jusqu'à -21 °C "
          ],
          "Exposition ": [
            "  ",
            " ",
            "  ensoleillée à mi-ombre "
          ],
          "Sol": "humifère",
          "Acidité ": "légèrement acide à acide",
          "Humidité ": "normal à frais",
          "Utilisation": "en isolé, en massif",
          "Plantation": "automne et printemps",
          "Multiplication": "boutures, marcottage, semis"
        },
        {
          "Nom": "Pavier blanc, Marronnier nain",
          "N. scientifique ": "Aesculus parviflora",
          "Synonyme ": "Aesculus macrostachya",
          "Famille ": "Hippocastanacées",
          "Origine ": "Etats-Unis",
          "Floraison": "juillet",
          "Fleurs ": [
            "     ",
            "   blanc "
          ],
          "Type": "arbuste, petit arbre",
          "Végétation": "vivace",
          "Feuillage ": "caduc",
          "Hauteur": "3 à 5 m",
          "Rusticité ": [
            "  ",
            " ",
            "  rustique, -19°C "
          ],
          "Exposition ": [
            "  ",
            " ",
            "  soleil à mi-ombre "
          ],
          "Sol": "limono argileux, riche",
          "Acidité ": "moyennement acide à moyennement basique",
          "Humidité ": "frais",
          "Utilisation": "massif, lisière, arbre isolé",
          "Plantation": "printemps",
          "Multiplication": "boutures, semis"

        },
    {
      "Nom": "Magnolia d'été, Magnolia à grandes fleurs",
      "N. scientifique ": "Magnolia grandiflora",
      "Famille ": "Magnoliacées",
      "Origine ": "Amérique du nord",
      "Floraison": "été",
      "Fleurs ": [
        "     ",
        "   blanc-crème "
      ],
      "Type": "arbre",
      "Végétation": "vivace",
      "Feuillage ": "persistant",
      "Hauteur": "jusqu'à 30 m selon les variétés",
      "Rusticité ": [
        "  ",
        " ",
        " ",
        "  rustique, de -25°C à -30°C selon les variétés "
      ],
      "Exposition ": [
        "  ",
        " ",
        "  soleil, mi-ombre "
      ],
      "Sol": "riche en humus",
      "Acidité ": "acide, pas de terre de bruyère pure car pauvre",
      "Humidité ": "bien frais",
      "Utilisation": "isolé",
      "Plantation": "printemps",
      "Multiplication": "semis, bouturage en septembre, marcottage",
      "Taille": "Pas de taille nécessaire. Si une taille doit être faite, pratiquez-la après la floraison.",
      "Sensibilité ": "résistant aux parasites et aux maladies"
    },
    {
      "Nom": "Heptacodion de Chine, Arbre à 7 fleurs",
      "N. scientifique ": "Heptacodium jasminoides",
      "Synonyme ": "Heptacodium miconioides",
      "Famille ": "Caprifoliacées",
      "Origine ": "Chine",
      "Floraison": "fin d'été",
      "Fleurs ": [
        "     ",
        "   blanc rosé "
      ],
      "Type": "petit arbre ornemental",
      "Végétation": "vivace",
      "Feuillage ": "caduc",
      "Hauteur": "4 à 5 m, rarement 8",
      "Rusticité ": [
        "  ",
        " ",
        " ",
        "  très rustique jusqu'à -34 °C "
      ],
      "Exposition ": [
        "  ",
        " ",
        "  ensoleillée à mi-ombre "
      ],
      "Sol": "à tendance argileuse ou sablonneuse",
      "Acidité ": "acide à légèrement alcalin",
      "Humidité ": "normal",
      "Utilisation": "isolé, en  massif",
      "Plantation": "automne, printemps",
      "Multiplication": "bouture, semis"
    },
    {
      "Nom": "Hortensia, Hydrangéa",
      "N. scientifique ": "Hydrangea",
      "Famille ": "Hydrangeacées, Philadelphacées",
      "Origine ": "Amérique du nord, Japon",
      "Floraison": "de juillet à septembre",
      "Fleurs ": "        rose, rouge, bleu, blanc ",
      "Type": "arbuste à fleurs",
      "Végétation": "vivace",
      "Feuillage ": "caduc",
      "Hauteur": "2 m",
      "Toxicité": " toxique",
      "Rusticité ": [
        "  ",
        " ",
        "   rustique "
      ],
      "Exposition ": [
        "  ",
        " ",
        "  soleil, mi-ombre, orientation nord-ouest idéale "
      ],
      "Sol": " riche en humus, 1/3 de terre de jardin avec 2/3 de terre pour plantes de terre de bruyère",
      "Acidité ": "acide pour les variétés à fleurs bleues, neutre, non calcaire",
      "Humidité ": "frais",
      "Utilisation": "isolé, haie libre, isolé, massif, bac",
      "Plantation": "printemps, automne",
      "Multiplication": "semis en mars, bouturage de juillet à septembre",
      "Taille": "Après les froids de mars enlevez les fleurs fanées. Vous pouvez rajeunir ou maîtriser la densité de vos hortensias en taillant vos plantes au printemps en rabattant au raz du sol les plus vieux rameaux. ",
      "Sensibilité ": "les cochenilles, les acariens, l'oïdium, l'ascochyta ( taches noires sur les feuilles ), la pourriture grise ( feuilles et tiges couvertes d'un duvet gris )"
    },
    {
      "Nom": "Hortensia YOU and ME 'Perfection'",
      "N. scientifique ": "Hydrangea macrophylla YOU and ME 'Perfection'",
      "Famille ": "Hydrangeacées, Philadelphacées",
      "Origine ": "Japon",
      "Floraison": "juillet à octobre",
      "Fleurs ": [
        "     ",
        "   rose, bleu "
      ],
      "Type": "arbuste d'ornement",
      "Végétation": "vivace",
      "Feuillage ": "caduc",
      "Hauteur": "0,90 m",
      "Rusticité ": [
        "  ",
        " ",
        " ",
        "  très rustique, -30°C "
      ],
      "Exposition ": [
        "  ",
        "  mi-ombre "
      ],
      "Sol": "humifère",
      "Acidité ": "fortement acide à neutre",
      "Humidité ": "frais à humide",
      "Utilisation": "massif, lisière mi-ombre, bouquet",
      "Plantation": "printemps",
      "Multiplication": "bouture"
    },
    {
      "Nom": "Hortensia velu, Hydrangéa velu",
      "N. scientifique ": "Hydrangea villosa",
      "Synonyme ": "Hydrangea aspera subsp villosa",
      "Famille ": "Hydrangeacées, Philadelphacées",
      "Origine ": "Asie",
      "Floraison": "juin à août",
      "Fleurs ": [
        "     ",
        "   violacée "
      ],
      "Type": "arbuste d'ornement",
      "Végétation": "vivace",
      "Feuillage ": "caduc",
      "Hauteur": "2 à 3 m",
      "Rusticité ": [
        "  ",
        " ",
        " ",
        "  très rustique, -24 °C "
      ],
      "Exposition ": [
        "  ",
        "  mi-ombre "
      ],
      "Sol": "humifère",
      "Acidité ": "moyennement acide à légèrement basique",
      "Humidité ": "frais à humide",
      "Utilisation": "massif, lisière",
      "Plantation": "printemps, fin d'été",
      "Multiplication": "bouture, marcottage"
    },
    {
      "Nom": "Hortensia nain",
      "N. scientifique ": "Hydrangea involucrata",
      "Famille ": "Hydrangeacées, Philadelphacées",
      "Origine ": "Japon",
      "Floraison": "juillet à octobre",
      "Fleurs ": [
        "     ",
        "   bleutée "
      ],
      "Type": "arbuste d’ornement",
      "Végétation": "vivace",
      "Feuillage ": "caduc",
      "Hauteur": "0,80 à 1,20 m",
      "Rusticité ": "   très rustique, -24°C ",
      "Exposition ": [
        "  ",
        "  mi-ombre "
      ],
      "Sol": "humifère",
      "Acidité ": "moyennement acide à moyennement basique",
      "Humidité ": "frais à humide",
      "Utilisation": "massif, lisière mi-ombre",
      "Plantation": "printemps, fin d’été",
      "Multiplication": "bouture, marcottage"
    },
    {
      "Nom": "Tamaris d'été",
      "N. scientifique ": "Tamarix ramosissima",
      "Synonymes ": "Tamarix aestivali, Tamarix odessana",
      "Famille ": "Tamaricacées",
      "Origine ": "Asie de l'Est, Russie du Sud jusqu'en Chine",
      "Floraison": "juin à septembre",
      "Fleurs ": [
        "     ",
        "     ",
        "     ",
        "   rose,blanc,pourpre "
      ],
      "Type": "arbuste ornemental",
      "Végétation": "arbustive",
      "Feuillage ": "caduc",
      "Hauteur": "4 m à 8 m",
      "Rusticité ": [
        "  ",
        " ",
        " ",
        "  très rustique, jusqu'à -20 °C "
      ],
      "Exposition ": [
        "  ",
        "  ensoleillée "
      ],
      "Sol": "très tolérant",
      "Acidité ": "acide à légèrement alcalin",
      "Humidité ": "sec à frais, il peut être inondé ponctuellement",
      "Utilisation": "isolé en haute-tige, fond de massif, haie, bord de mer",
      "Plantation": "automne, printemps",
      "Multiplication": "bouture, semis, marcotte"
    },
    {
      "Nom": "Tamaris",
      "N. scientifique ": "Tamarix",
      "Famille ": "Tamaricacées",
      "Origine ": "Asie, Europe",
      "Floraison": "mai à août",
      "Fleurs ": [
        "     ",
        "   rose "
      ],
      "Type": "arbuste à fleurs",
      "Végétation": "vivace",
      "Feuillage ": "caduc",
      "Hauteur": "6 m",
      "Rusticité ": [
        "  ",
        " ",
        "  rustique "
      ],
      "Exposition ": [
        "  ",
        "  soleil "
      ],
      "Sol": "ordinaire, léger",
      "Acidité ": "neutre",
      "Humidité ": "normal, sec",
      "Utilisation": "isolé, haie brise vent, haie libre",
      "Plantation": "printemps, automne",
      "Multiplication": "bouture à l'automne",
      "Taille": "Rabattez sévèrement après la floraison pour conserver un port compact",
      "Sensibilité ": "résistant aux maladies et aux parasites"
    },
    {
      "Nom": "Spirée du Japon",
      "N. scientifique ": "Spiraea japonica",
      "Famille ": "Rosacées",
      "Origine ": "Japon, Chine",
      "Floraison": "été",
      "Fleurs ": "        rose, blanc ",
      "Type": "arbuste à fleurs",
      "Végétation": "vivace",
      "Feuillage ": "caduc",
      "Hauteur": "jusqu'à 1,5m",
      "Rusticité ": [
        "  ",
        " ",
        " ",
        "  très rustique "
      ],
      "Exposition ": [
        "  ",
        " ",
        "  soleil, mi-ombre "
      ],
      "Sol": "riche, drainé",
      "Acidité ": "neutre",
      "Humidité ": "frais",
      "Utilisation": "massif, isolé, couvre-sol pour les variétés naines, bacs",
      "Plantation": "printemps, automne",
      "Multiplication": "semis au printemps, bouturage en été",
      "Sensibilité ": "résistant aux maladies"
    },
    {
      "Nom": "Spirée bleue, Barbe bleue",
      "N. scientifique ": "Caryopteris",
      "Famille ": "Verbénacées",
      "Origine ": "Asie",
      "Floraison": "août, septembre, octobre",
      "Fleurs ": [
        "     ",
        "   bleu intense "
      ],
      "Type": "arbuste à fleurs",
      "Végétation": "vivace",
      "Feuillage ": "caduc",
      "Hauteur": "de 60 cm à 1,20 m",
      "Rusticité ": [
        "  ",
        " ",
        " ",
        "  -15 °C pour les hybrides, les espèces pures sont plus frileuses et supportent entre - 5 °C et - 10 °C, sauf C. incana qui tolère -20 °C "
      ],
      "Exposition ": [
        "  ",
        "  soleil "
      ],
      "Sol": "ordinaire, léger, bien drainé, même pauvre et caillouteux",
      "Acidité ": "neutre, calcaire accepté",
      "Humidité ": "normal",
      "Utilisation": "massif, haie basse, fleurs coupées, bac",
      "Plantation": "plantation au printemps",
      "Multiplication": "bouturage au printemps ou en été",
      "Taille": "le caryoptéris a pour seule exigence une taille sévère chaque année. Supprimez toute la partie aérienne à 5 cm environ de la souche. Il faut couper sur les bourgeons (yeux) situés le plus près possible de la souche ligneuse, mais également réduire le nombre de rameaux, car le buisson devient très touffu au fil des années. Intervenez plutôt en automne dans les régions au climat froid, vous pourrez mieux protéger la souche et la plante offrira moins de prise au gel. Dans les zones plus privilégiées, une taille printanière permet un démarrage plus rapide si elle se pratique dès que le bois reperce. Pour lui maintenir une forme très compacte, taillez-le de préférence au printemps. Si vous souhaitez le laisser un peu grandir, taillez-le juste après la floraison.",
      "Sensibilité ": "Cet arbuste n'est pour ainsi dire jamais attaqué par les maladies."
    },
    {
      "Nom": "Sorbier fausse spirée, Sorbaire à feuilles de sorbier",
      "N. scientifique ": "Sorbaria sorbifolia",
      "Synonymes ": "Schizonotus sorbifolius,  Spiraea sorbifolia",
      "Famille ": "Rosacées",
      "Origine ": "Asie : Chine du Nord, Japon, Sibérie",
      "Floraison": "juin, juillet",
      "Fleurs ": [
        "     ",
        "   blanc "
      ],
      "Type": "large arbuste décoratif",
      "Végétation": "vicace",
      "Feuillage ": "caduc",
      "Hauteur": "1,50 à 2 m",
      "Rusticité ": [
        "  ",
        " ",
        " ",
        "  très rustique, jusqu'à -34 °C "
      ],
      "Exposition ": [
        "  ",
        " ",
        "  mi-ombre à ensoleillée "
      ],
      "Sol": "tolérant",
      "Acidité ": "acide à légèrement basique",
      "Humidité ": "normal",
      "Utilisation": "jardin paysagé",
      "Plantation": "automne, printemps"
    },
    {
      "Nom": "Sauge germandrée, Sauge bleue du Mexique",
      "N. scientifique ": "Salvia chamaedryoïdes",
      "Famille ": "Labiacées, Lamiacées, Labiées",
      "Origine ": "Mexique et Texas",
      "Floraison": "août à septembre",
      "Fleurs ": [
        "     ",
        "   bleu "
      ],
      "Type": "arbustive à fleurs",
      "Végétation": "vivace",
      "Feuillage ": "caduc",
      "Hauteur": "30 à 45 cm",
      "Rusticité ": [
        "  ",
        " ",
        "  rustique, -12°C "
      ],
      "Exposition ": [
        "  ",
        "  ensoleillée à mi-ombre "
      ],
      "Sol": "léger et drainant",
      "Acidité ": "légèrement acide à légèrement alcalin",
      "Humidité ": "normal à sec",
      "Utilisation": "massif, potée",
      "Plantation": "printemps",
      "Multiplication": "bouture, semis"
    },
    {
      "Nom": "Sauge d’automne, Sauge de Gregg, Sauge du Texas",
      "N. scientifique ": "Salvia greggii",
      "Famille ": "Labiacées, Lamiacées, Labiées",
      "Origine ": "Mexique et Texas",
      "Floraison": "avril à septembre",
      "Fleurs ": "        rouge, rose, blanc, violet, orange ",
      "Type": "arbustive",
      "Végétation": "vivace",
      "Feuillage ": "semi-persistant",
      "Hauteur": "50 à 120 cm",
      "Rusticité ": [
        "  ",
        " ",
        "  rustique -15°C "
      ],
      "Exposition ": [
        "  ",
        " ",
        "  soleil à mi-ombre "
      ],
      "Sol": "drainant, calcaire, sablonneux ou limoneux",
      "Acidité ": "légèrement acide à alcalin",
      "Humidité ": "normal à sec",
      "Utilisation": "massif, potée, haie basse, plante aromatique",
      "Plantation": "printemps",
      "Multiplication": "bouture, semis, marcotte"
    },
    {
      "Nom": "Sauge de Graham Hot Lips",
      "N. scientifique ": "Salvia microphylla 'Hot Lips'",
      "Famille ": "Labiacées, Lamiacées, Labiées",
      "Origine ": "Mexique",
      "Floraison": "mai jusqu'aux gelées",
      "Fleurs ": [
        "     ",
        "   rouges et blanches "
      ],
      "Type": "arbustive",
      "Végétation": "vivace",
      "Feuillage ": "caduc",
      "Hauteur": "50 à 120 cm ",
      "Rusticité ": [
        "  ",
        " ",
        "  rustique jusqu'à -16°C "
      ],
      "Exposition ": [
        "  ",
        "  ensoleillée "
      ],
      "Sol": "drainant",
      "Acidité ": "légèrement acide à légèrement alcalin",
      "Humidité ": "normal à sec",
      "Utilisation": "massif, potée, haie basse",
      "Plantation": "printemps",
      "Multiplication": "bouture"
    },
    {
      "Nom": "Sauge de Graham",
      "N. scientifique ": "Salvia microphylla",
      "Synonyme ": "Salvia grahamii",
      "Famille ": "Labiacées, Lamiacées, Labiées",
      "Origine ": "Mexique",
      "Floraison": "de mai aux gelées",
      "Fleurs ": "        rouge, jaune, rose ",
      "Type": "arbuste à fleurs",
      "Végétation": "vivace",
      "Feuillage ": "caduc",
      "Hauteur": "120 m",
      "Rusticité ": [
        "  ",
        " ",
        "  -12°C, rustique "
      ],
      "Exposition ": [
        "  ",
        "  soleil "
      ],
      "Sol": "ordinaire, bien drainé",
      "Acidité ": "neutre",
      "Humidité ": "normal",
      "Utilisation": "haie libre, bordure, massif, pot",
      "Plantation": "printemps, dans les sols retenant l'eau, mettez une bonne couche de graviers pour assurer un bon drainage pendant l'hiver.",
      "Multiplication": "semis, bouturage",
      "Taille": "rabattez la sévèrement en mars",
      "Sensibilité ": "les limaces, les pucerons"
    },
    {
      "Nom": "Sauge à feuilles de serpolet, Sauge  de Graham violette",
      "N. scientifique ": "Salvia serpyllifolia",
      "Famille ": "Labiacées, Lamiacées, Labiées",
      "Origine ": "Mexique",
      "Floraison": "mai jusqu'aux gelées",
      "Fleurs ": [
        "     ",
        "   violet "
      ],
      "Type": "arbustive",
      "Végétation": "vivace",
      "Feuillage ": "caduc",
      "Hauteur": "30 à 60 cm ",
      "Rusticité ": [
        "  ",
        " ",
        "  rustique, jusqu'à -11 °C "
      ],
      "Exposition ": [
        "  ",
        "  ensoleillée "
      ],
      "Sol": "drainant",
      "Acidité ": "légèrement acide à légèrement alcalin",
      "Humidité ": "normal à sec",
      "Utilisation": "massif, potée, haie basse",
      "Plantation": "printemps",
      "Multiplication": "bouture"
    },
    {
      "Nom": "Santoline petit-cyprès",
      "N. scientifique ": "Santolina chamaecyparissus",
      "Famille ": "Astéracées, Composées",
      "Origine ": "bassin méditerranéen",
      "Floraison": "juin à août",
      "Fleurs ": [
        "     ",
        "   jaune "
      ],
      "Type": "sous-arbrisseau",
      "Végétation": "vivace",
      "Feuillage ": "persistant",
      "Hauteur": "50 cm",
      "Rusticité ": "   rustique - 15°C ",
      "Exposition ": [
        "  ",
        "  ensoleillée "
      ],
      "Sol": "pauvre et drainant",
      "Acidité ": "indifférent",
      "Humidité ": "normal à sec",
      "Utilisation": "massif, haie basse, couvre-sol",
      "Plantation": "printemps, automne",
      "Multiplication": "bouture, semis"
    },
    {
      "Nom": "Rosier rugueux, Rosier du Japon",
      "N. scientifique ": "Rosa rugosa",
      "Famille ": "Rosacées",
      "Origine ": "Chine, Japon, Corée",
      "Floraison": "de mai aux gelées",
      "Fleurs ": [
        "     ",
        "     ",
        "     ",
        "   rouge, rose, blanc "
      ],
      "Type": "arbuste à fleurs",
      "Végétation": "vivace",
      "Feuillage ": "caduc",
      "Hauteur": "de 1 à 2 m selon les variétés",
      "Toxicité": "Gare aux épines",
      "Rusticité ": [
        "  ",
        " ",
        "  rustique "
      ],
      "Exposition ": [
        "  ",
        "  soleil "
      ],
      "Sol": "plutôt riche, drainé ",
      "Acidité ": "neutre",
      "Humidité ": "plutôt frais",
      "Utilisation": "massif, haie défensive",
      "Plantation": "printemps et automne pour les plantes à racines nues",
      "Multiplication": "semis, séparation des rejets pour les formes botaniques, boutures",
      "Taille": "en mars, éliminez les rameaux abîmés et les plus vieilles branches. rabattez légèrement pour remettre en forme votre rosier. supprimez les rejets sans intérêt des variétés greffées (sur Rosa canina, l'églantier)"
    },
    {
      "Nom": "Rosier pimprenelle",
      "N. scientifique ": "Rosa pimpinellifolia",
      "Synonyme ": "Rosa spinosissima",
      "Famille ": "Rosacées",
      "Origine ": "Europe",
      "Floraison": "juin -juillet",
      "Fleurs ": [
        "     ",
        "   blanc crème "
      ],
      "Type": "rosier botanique",
      "Végétation": "arbustive",
      "Feuillage ": "caduc",
      "Hauteur": "80 cm à 1 m 20",
      "Rusticité ": [
        "  ",
        " ",
        " ",
        "  très rustique, -25 °C "
      ],
      "Exposition ": [
        "  ",
        " ",
        "  ensoleillée à mi-ombre "
      ],
      "Sol": "drainant, minéral et pauvre",
      "Acidité ": "neutre à  basique",
      "Humidité ": "normal à légèrement sec",
      "Utilisation": "haie défensive, lisière",
      "Plantation": "automne, printemps",
      "Multiplication": "boutures, marcottes, semis, divisions"
    },
    {
      "Nom": "Rosier paysager 'Vesuvia'",
      "N. scientifique ": "Rosa x Décorosiers® 'VESUVIA'",
      "Synonyme ": "Rosa x 'Noare'",
      "Famille ": "Rosacées",
      "Origine ": "horticole",
      "Floraison": "mai à novembre",
      "Fleurs ": [
        "     ",
        "   rouge "
      ],
      "Type": "rosier paysager",
      "Végétation": "arbustive",
      "Feuillage ": "caduc",
      "Hauteur": "0,60 à 0,90 cm",
      "Rusticité ": [
        "  ",
        " ",
        "  rusique, jusqu'à -18°C "
      ],
      "Exposition ": [
        "  ",
        " ",
        "  soleil à mi-ombre "
      ],
      "Sol": "très tolérant, sauf sols trop calcaires",
      "Acidité ": "acide à légèrement basique",
      "Humidité ": "normal à un peu sec",
      "Utilisation": "haie basse, couvre-sol, talus, massif",
      "Plantation": "automne, printemps",
      "Multiplication": "boutures, marcottes, greffe, mais la reproduction est soumise à des droits d'obtenteur"
    },
    {
      "Nom": "Rosier musqué, Rose musquée",
      "N. scientifique ": "Rosa moschata",
      "Synonymes ": "Rosa moschata var. nastarana, Rosa pissartii",
      "Famille ": "Rosacées",
      "Origine ": "Asie ou Moyen-Orient",
      "Floraison": "juin jusqu'aux gelées",
      "Fleurs ": [
        "     ",
        "   blanc "
      ],
      "Type": "rosier botanique",
      "Végétation": "arbustive",
      "Feuillage ": "caduc",
      "Hauteur": "2 à 3 m",
      "Rusticité ": [
        "  ",
        " ",
        "  rustique, jusqu'à -19 °C "
      ],
      "Exposition ": [
        "  ",
        " ",
        "  ensoleillée à mi-ombre "
      ],
      "Sol": "argilo-siliceux",
      "Acidité ": "acide",
      "Humidité ": "normal à sec",
      "Utilisation": "haie, massif, collection",
      "Plantation": "automne, printemps",
      "Multiplication": "boutures, marcottes, semis"
    },
    {
      "Nom": "Rosier multiflore",
      "N. scientifique ": "Rosa multiflora",
      "Famille ": "Rosacées",
      "Origine ": "Asie",
      "Floraison": "juin -juillet",
      "Fleurs ": [
        "     ",
        "   blanc "
      ],
      "Type": "rosier botanique",
      "Végétation": "arbustive, semi-grimpante",
      "Feuillage ": "caduc",
      "Hauteur": "2 à 3 m",
      "Rusticité ": [
        "  ",
        " ",
        " ",
        "  très rustique, -37 °C "
      ],
      "Exposition ": [
        "  ",
        " ",
        "  ensoleillée à mi-ombre "
      ],
      "Sol": "très tolérant",
      "Acidité ": "acide à légèrement acide",
      "Humidité ": "normal",
      "Utilisation": "haie, lisère, porte-greffe",
      "Plantation": "automne, printemps",
      "Multiplication": "boutures, marcottes, semis, divisions"
    },
    {
      "Nom": "Rosier du père Hugo, Rosier jaune de Chine",
      "N. scientifique ": "Rosa hugonis",
      "Synonyme ": "Rosa Xanthina",
      "Famille ": "Rosacées",
      "Origine ": "centre de la Chine",
      "Floraison": "mai à juin",
      "Fleurs ": [
        "     ",
        "   jaune "
      ],
      "Type": "rosier botanique",
      "Végétation": "arbustive",
      "Feuillage ": "caduc",
      "Hauteur": "2 m à 2,50 m",
      "Rusticité ": [
        "  ",
        " ",
        " ",
        "  très rustique jusqu'à -25 °C "
      ],
      "Exposition ": [
        "  ",
        " ",
        "  ensoleillée à mi-ombre "
      ],
      "Sol": "relativement drainant",
      "Acidité ": "acide à légèrement basique",
      "Humidité ": "normal à sec",
      "Utilisation": "arbuste ornemental en haie libre, ou en isolé",
      "Plantation": "automne, printemps",
      "Multiplication": "boutures, marcottes, semis"
    },
    {
      "Nom": "Rosier de Wichura",
      "N. scientifique ": "Rosa wichuraiana",
      "Synonyme ": "Rosa luciae var wichuraiana",
      "Famille ": "Rosacées",
      "Origine ": "Asie orientale",
      "Floraison": "juin -juillet",
      "Fleurs ": [
        "     ",
        "   blanc "
      ],
      "Type": "rosier botanique grimpant",
      "Végétation": "arbustive",
      "Feuillage ": "semi-persistant",
      "Hauteur": "2 à 5 m",
      "Rusticité ": [
        "  ",
        " ",
        " ",
        "  très rustique jusqu'à -24 °C "
      ],
      "Exposition ": [
        "  ",
        " ",
        "  ensoleillée à mi-ombre "
      ],
      "Sol": "argilo-siliceux, même lourd",
      "Acidité ": "neutre à  basique",
      "Humidité ": "normal",
      "Utilisation": "haie défensive, lisière, pergola",
      "Plantation": "automne, printemps",
      "Multiplication": "boutures, marcottes, semis, divisions"
    },
    {
      "Nom": "Rosier de France",
      "N. scientifique ": "Rosa gallica",
      "Famille ": "Rosacées",
      "Origine ": "Europe méridionale, Europe centrale et Asie",
      "Floraison": "mai-juin",
      "Fleurs ": [
        "     ",
        "   rose "
      ],
      "Type": "rosier botanique",
      "Végétation": "arbustive",
      "Feuillage ": "caduc",
      "Hauteur": "80 cm",
      "Rusticité ": [
        "  ",
        " ",
        " ",
        "  très rustique, -29°C "
      ],
      "Exposition ": [
        "  ",
        " ",
        "  ensoleillée à mi-ombre "
      ],
      "Sol": "un peu lourd",
      "Acidité ": "légèrement acide à légèrement basique",
      "Humidité ": "normal à légèrement sec",
      "Utilisation": "massif",
      "Plantation": "automne, printemps",
      "Multiplication": "boutures, marcottes, semis"
    },
    {
      "Nom": "Rosier de Chine changeant, Rose papillon",
      "N. scientifique ": "Rosa chinensis 'Mutabilis'",
      "Synonymes ": "Rosa indica, Rosa chinensis var spontanea",
      "Famille ": "Rosacées",
      "Origine ": "Chine",
      "Floraison": "d'avril jusqu'aux gelées",
      "Fleurs ": [
        "     ",
        "     ",
        "     ",
        "   jaune, rose, magenta, orange "
      ],
      "Type": "rosier ancien à fleurs simples",
      "Végétation": "arbustive",
      "Feuillage ": "semi-persistant",
      "Hauteur": "1,20  à 2,50 m",
      "Rusticité ": [
        "  ",
        " ",
        "  rustique jusqu'à -12 °C "
      ],
      "Exposition ": [
        "  ",
        " ",
        "  ensoleillée à mi-ombre "
      ],
      "Sol": "tolérant",
      "Acidité ": "moyennement acide à peu basique",
      "Humidité ": "frais à très sec une fois bien installé",
      "Utilisation": "arbuste ornementale, haie libre",
      "Plantation": "automne, printemps",
      "Multiplication": "boutures, marcottes, semis, divisions"
    },
    {
      "Nom": "Rosier de chine",
      "N. scientifique ": "Rosa chinensis",
      "Synonymes ": "Rosa indica, Rosa chinensis var spontanea",
      "Famille ": "Rosacées",
      "Origine ": "Chine",
      "Floraison": "de juin jusqu'aux gelées",
      "Fleurs ": [
        "     ",
        "   rose à rouge "
      ],
      "Type": "rosier botanique",
      "Végétation": "arbustive",
      "Feuillage ": "caduc",
      "Hauteur": "1m 30 à 2 m",
      "Rusticité ": [
        "  ",
        " ",
        "  rustique, jusqu'à -19 °C "
      ],
      "Exposition ": [
        "  ",
        " ",
        "  ensoleillée à mi-ombre "
      ],
      "Sol": "tolérant",
      "Acidité ": "moyennement acide à moyennement basique",
      "Humidité ": "normal à sec",
      "Utilisation": "arbuste ornementale, haie libre",
      "Plantation": "automne, printemps",
      "Multiplication": "boutures, marcottes, semis, divisions"
    },
    {
      "Nom": "Rosier",
      "N. scientifique ": "Rosa",
      "Famille ": "Rosacées",
      "Origine ": "Asie",
      "Floraison": "printemps, été",
      "Fleurs ": [
        "     ",
        "     ",
        "     ",
        "     ",
        "     ",
        "     ",
        "     ",
        "     ",
        "     ",
        "   variées "
      ],
      "Type": "arbuste à fleurs, plante grimpante",
      "Végétation": "vivace",
      "Feuillage ": "caduc",
      "Hauteur": "3 m",
      "Rusticité ": [
        "  ",
        " ",
        "  rustique mais protégez le point de greffe par un buttage de 20 cm "
      ],
      "Exposition ": [
        "  ",
        "  soleil, à l'abri du vent "
      ],
      "Sol": "terre à tendance argileuse, riche, bien drainé pour ne pas asphyxier les racines",
      "Acidité ": "neutre, acide, éviter les sols trop calcaire",
      "Humidité ": "normal",
      "Utilisation": "massif, haie, couvre-sol, isolée sur une pelouse, grimpant, bac, pot",
      "Plantation": "rosiers à racines nues d'octobre à avril, rosiers en conteneur à planter toute l'année. éviter les périodes de sécheresse et les jours de gel. Notre fiche sur la plantation des rosiers",
      "Multiplication": "semis en mars, bouturage en septembre-octobre , greffage",
      "Taille": "taille des rosiers",
      "Sensibilité ": "les taches noires, l'oïdium, la chlorose, les pucerons, les cochenilles"
    },
    {
      "Nom": "Potentille arbustive",
      "N. scientifique ": "Potentilla fruticosa",
      "Famille ": "Rosacées",
      "Origine ": "Hémisphère nord",
      "Floraison": "de mai à octobre",
      "Fleurs ": "        jaune, orange, rose, rouge ",
      "Type": "arbuste à fleurs",
      "Végétation": "vivace",
      "Feuillage ": "caduc",
      "Hauteur": "de 30 cm 1,5 m",
      "Rusticité ": [
        "  ",
        " ",
        " ",
        "  -25°C, très rustique "
      ],
      "Exposition ": [
        "  ",
        " ",
        "  soleil, mi-ombre pour les variétés colorées "
      ],
      "Sol": "ordinaire, sableux, bien drainé, évitez les terres lourdes ou inondées",
      "Acidité ": "neutre à calcaire",
      "Humidité ": "normal, sec",
      "Utilisation": "massif, haie basse, haie fleurie, couvre-sol, bac",
      "Plantation": "automne, printemps",
      "Multiplication": "bouturage facile fin août, bouturage à bois sec de novembre à février est aussi très facile",
      "Taille": "Taillez chaque année au départ de la végétation pour stimuler la floraison et conserver une forme buissonnante.",
      "Sensibilité ": "parfois l'oïdium, les pucerons, les araignées rouges"
    },
    {
      "Nom": "Poivre de Tasmanie",
      "N. scientifique ": "Tasmannia lanceolata",
      "Synonymes ": "Drimys lanceolata, Winterania lanceolata, Drimys aromatica",
      "Famille ": "Wintéracées",
      "Origine ": "Australie",
      "Floraison": "été",
      "Fleurs ": [
        "     ",
        "   crème "
      ],
      "Type": "arbuste persistant pour climat doux et humide",
      "Végétation": "arbustive",
      "Feuillage ": "persistant",
      "Hauteur": "2 à 4 m",
      "Rusticité ": [
        "  ",
        " ",
        "  rustique, -15°C "
      ],
      "Exposition ": [
        "  ",
        "  ensoleillée "
      ],
      "Sol": "riche et humifère",
      "Acidité ": "acide à neutre",
      "Humidité ": "normal à frais",
      "Utilisation": "en isolé, massif, haie, plante condimentaire",
      "Plantation": "automne jusqu’à mars"
    },
    {
      "Nom": "Physocarpe, Bois aux sept écorces",
      "N. scientifique ": "Physocarpus",
      "Famille ": "Rosacées",
      "Origine ": "Asie de l'est, Amérique du nord",
      "Floraison": "juin",
      "Fleurs ": [
        "     ",
        "   blanc "
      ],
      "Type": "arbuste à fleurs",
      "Végétation": "vivace",
      "Feuillage ": "caduc",
      "Hauteur": "de 1 à 3 m selon les espèces et les variétés",
      "Rusticité ": [
        "  ",
        " ",
        " ",
        "  très rustique, jusqu'à - 20 à - 25 °C "
      ],
      "Exposition ": [
        "  ",
        " ",
        "  soleil, mi-ombre "
      ],
      "Sol": "fertile, bien drainé",
      "Acidité ": "un peu acide",
      "Humidité ": "frais",
      "Utilisation": "haie libre, bac",
      "Plantation": "en automne",
      "Multiplication": "Semis en godet à l’extérieur, en mars après stratification des graines ou en octobre juste après la récolte. Boutures herbacées en juin sous abri, à l’étouffée, avec une légère chaleur de fond. Séparation de rejets d’octobre à fin mars.",
      "Taille": "Taillez après la floraison en défourchant les branches principales pour aérer le centre de la touffe. Réduisez chaque année la longueur des branches principales d’un tiers environ. Les très vieux sujets dégarnis de la base peuvent être entièrement recépés (coupés au ras du sol).",
      "Sensibilité ": "résistant aux maladies et aux insectes"
    },
    {
      "Nom": "Millepertuis inodore",
      "N. scientifique ": "Hypericum x inodorum",
      "Famille ": "Clusiacées, Guttifères",
      "Origine ": "hybride d'origine indéterminée",
      "Floraison": "juillet à septembre",
      "Fleurs ": [
        "     ",
        "   jaune "
      ],
      "Type": "arbuste ornemental",
      "Végétation": "vivace semi-arbustive",
      "Feuillage ": "semi-persistant",
      "Hauteur": "0.50 à 1 m 20",
      "Rusticité ": "   rustique, -15°C ",
      "Exposition ": [
        "  ",
        "  ensoleillée à mi-ombre "
      ],
      "Sol": "fertile",
      "Acidité ": "indifférent",
      "Humidité ": "frais",
      "Utilisation": "massif, rocaille, bordure, bouquet",
      "Plantation": "automne jusqu’à avril",
      "Multiplication": "boutures",
      "Sensibilité ": "rouille"
    },
    {
      "Nom": "Millepertuis",
      "N. scientifique ": "Hypericum",
      "Famille ": "Clusiacées, Guttifères",
      "Origine ": "Hémisphère nord",
      "Floraison": "de juin à octobre",
      "Fleurs ": [
        "     ",
        "   jaune "
      ],
      "Type": "petit arbuste à fleurs",
      "Végétation": "vivace, vivace arbustive",
      "Feuillage ": "variable selon les espèces",
      "Hauteur": "de 20 à 30 cm",
      "Rusticité ": [
        "  ",
        " ",
        "  rustique "
      ],
      "Exposition ": [
        "  ",
        " ",
        "  soleil, mi-ombre "
      ],
      "Sol": "tout type de sol bien drainé",
      "Acidité ": "neutre",
      "Humidité ": "normal",
      "Utilisation": "couvre-sol, talus, haie libre, bordure, pot, bac",
      "Plantation": "le début de l’automne ou du printemps",
      "Multiplication": "division, marcottage, bouturage",
      "Taille": "au début du printemps , rabattez à la cisaille les espèces vivaces pour obtenir un tapis bien dense et taillez les arbustives un an sur deux pour obtenir un port compact",
      "Sensibilité ": "la rouille"
    },
    {
      "Nom": "Lilas de Perse",
      "N. scientifique ": "Syringa x persica",
      "Famille ": "Oléacées",
      "Origine ": "horticole",
      "Floraison": "mai, juin",
      "Fleurs ": [
        "     ",
        "   mauve "
      ],
      "Type": "arbuste",
      "Végétation": "arbustive",
      "Feuillage ": "caduc",
      "Hauteur": "2 m",
      "Rusticité ": [
        "  ",
        " ",
        " ",
        "  très rustique, -29°C "
      ],
      "Exposition ": [
        "  ",
        " ",
        "  mi-ombre à plein soleil "
      ],
      "Sol": "terre riche et bien drainée",
      "Acidité ": "neutre à basique",
      "Humidité ": "frais  ",
      "Utilisation": "en isolé, en massif",
      "Plantation": "automne, printemps",
      "Multiplication": "boutures, semis, division de rejet"
    },
    {
      "Nom": "Lespedeza de Thunberg",
      "N. scientifique ": "Lespedeza thunbergii",
      "Synonyme ": "Desmodium penduliflorum",
      "Famille ": "Légumineuses, Fabacées, Papilionacées",
      "Origine ": "Asie",
      "Floraison": "d’août jusqu’aux gelées",
      "Fleurs ": [
        "     ",
        "   pourpre "
      ],
      "Type": "plante semi-arbustive",
      "Végétation": "vivace",
      "Feuillage ": "caduc",
      "Hauteur": "1 à 2m",
      "Rusticité ": "   rustique - 15°C ",
      "Exposition ": [
        "  ",
        "  ensoleillée "
      ],
      "Sol": "tolérant",
      "Acidité ": "acide à neutre",
      "Humidité ": "normal",
      "Utilisation": "massif, talus",
      "Plantation": "printemps",
      "Multiplication": "séparation des rejets, semis",
      "Sensibilité ": "résistant aux maladies et peu sensible aux insectes"
    },
    {
      "Nom": "Lavatère en arbre, Mauve en arbre",
      "N. scientifique ": "Lavatera x",
      "Famille ": "Malvacées",
      "Origine ": "Bassin méditerranéen",
      "Floraison": "été, automne",
      "Fleurs ": [
        "     ",
        "   blanc, rose "
      ],
      "Type": "arbuste à fleurs, ou annuelle au port arbustif",
      "Végétation": "vivace, annuelle, bisannuelle",
      "Feuillage ": "caduc",
      "Hauteur": "de 1,5 à 3 m ",
      "Rusticité ": [
        "  ",
        " ",
        " ",
        "  -15°C "
      ],
      "Exposition ": [
        "  ",
        "  soleil "
      ],
      "Sol": "riche, léger, bien drainé",
      "Acidité ": "neutre",
      "Humidité ": "normal, n'apprécie pas l'humidité",
      "Utilisation": "isolé, haie libre, bac",
      "Plantation": "printemps, automne",
      "Multiplication": "semis à partir des graines récoltées, bouturage fin août, bouturage de rejet en juin",
      "Taille": "Rabattre au printemps, en laissant deux ou trois yeux ou à environ 50 cm du sol.",
      "Sensibilité ": "pourriture de la souche en hiver, rouille"
    },
    {
      "Nom": "Laurier rose 'Villa Romaine'",
      "N. scientifique ": "Nerium oleander 'Villa Romaine'",
      "Famille ": "Apocynacées",
      "Origine ": "Afrique du nord",
      "Floraison": "tout l’été",
      "Fleurs ": [
        "     ",
        "   rose "
      ],
      "Type": "plante méditerranéenne",
      "Végétation": "vivace",
      "Feuillage ": "persistant",
      "Hauteur": "150 à 250 cm",
      "Rusticité ": [
        "  ",
        " ",
        "  rustique jusqu’à -15°C "
      ],
      "Exposition ": [
        "  ",
        " ",
        "  ensoleillée à mi-ombre "
      ],
      "Sol": "léger et drainant",
      "Acidité ": "tolérant",
      "Humidité ": "normal à sec",
      "Utilisation": "massif, potée",
      "Plantation": "printemps",
      "Multiplication": "bouturage"
    },
    {
      "Nom": "Laurier d'Amérique, Laurier de montagnes",
      "N. scientifique ": "Kalmia latifolia",
      "Famille ": "Ericacées",
      "Origine ": "Amérique du nord",
      "Floraison": "juin, juillet",
      "Fleurs ": [
        "     ",
        "   blanche à rose "
      ],
      "Type": "arbuste d'ornement",
      "Végétation": "vivace",
      "Feuillage ": "persistant",
      "Hauteur": "1m",
      "Toxicité": "toute les parties de la plante sont toxiques",
      "Rusticité ": [
        "  ",
        " ",
        "  rustique jusqu'à - 27°C "
      ],
      "Exposition ": [
        "  ",
        "  mi-ombre "
      ],
      "Sol": "riche et drainant",
      "Acidité ": "acide",
      "Humidité ": "frais",
      "Utilisation": "massif, pourtour de bassin, sous-bois",
      "Plantation": "printemps, automne",
      "Multiplication": "bouture, marcottage, semis"
    }
         ]
}